hmd_lang_audit/__init__.py
hmd_lang_audit/audit_record.py
hmd_lang_audit/audit_record_audits_entity.py
hmd_lang_audit/hmd_lang_audit_client.py
hmd_lang_audit/schemas/hmd_lang_audit/audit_record.hms
hmd_lang_audit/schemas/hmd_lang_audit/audit_record_audits_entity.hms
hmd_lang_audit-0.1.3.dist-info/METADATA
hmd_lang_audit-0.1.3.dist-info/WHEEL
hmd_lang_audit-0.1.3.dist-info/top_level.txt
hmd_lang_audit-0.1.3.dist-info/RECORD
